automlhelper/__init__.py
automlhelper/automl.py
automlhelper/storageio.py
automlhelper-0.0.1.dist-info/LICENSE
automlhelper-0.0.1.dist-info/METADATA
automlhelper-0.0.1.dist-info/WHEEL
automlhelper-0.0.1.dist-info/top_level.txt
automlhelper-0.0.1.dist-info/RECORD
