Metadata-Version: 2.1
Name: automlhelper
Version: 0.0.1
Summary: Helper to automate Cloud AutoML (vision) operations
Home-page: https://github.com/N2BBrasil/automl-helper
Author: Samuel Heinrichs
Author-email: samuel@n2bbrasil.com
License: UNKNOWN
Platform: UNKNOWN
Classifier: Programming Language :: Python :: 3
Classifier: License :: OSI Approved :: MIT License
Classifier: Operating System :: OS Independent
Requires-Dist: cachetools
Requires-Dist: certifi
Requires-Dist: chardet
Requires-Dist: google-api-core
Requires-Dist: google-auth
Requires-Dist: google-cloud-automl
Requires-Dist: google-cloud-core
Requires-Dist: google-cloud-storage
Requires-Dist: google-resumable-media
Requires-Dist: googleapis-common-protos
Requires-Dist: grpcio
Requires-Dist: idna
Requires-Dist: numpy
Requires-Dist: protobuf
Requires-Dist: pyasn1
Requires-Dist: pyasn1-modules
Requires-Dist: python-dateutil
Requires-Dist: pytz
Requires-Dist: requests
Requires-Dist: rsa
Requires-Dist: six
Requires-Dist: urllib3
